Metadata-Version: 2.1
Name: beam-mysql-connector
Version: 1.8.4
Summary: MySQL I/O Connector of Apache Beam
Home-page: https://github.com/esaki01/beam-mysql-connector
Author: esakik
Author-email: esaki1011@gmail.com
License: MIT
Download-URL: https://pypi.python.org/pypi/beam-mysql-connector
Keywords: apache beam mysql connector
Platform: UNKNOWN
Classifier: License :: OSI Approved :: MIT License
Classifier: Programming Language :: Python :: 3.5
Classifier: Programming Language :: Python :: 3.6
Classifier: Programming Language :: Python :: 3.7
Classifier: Programming Language :: Python :: 3.8
Classifier: Programming Language :: Python :: 3.9
Requires-Python: >=3.5
